cmdbase_cli/__init__.py
cmdbase_cli/_version.py
cmdbase_cli-0.0.1a2.dist-info/LICENSE.txt
cmdbase_cli-0.0.1a2.dist-info/METADATA
cmdbase_cli-0.0.1a2.dist-info/WHEEL
cmdbase_cli-0.0.1a2.dist-info/top_level.txt
cmdbase_cli-0.0.1a2.dist-info/RECORD
