Metadata-Version: 2.1
Name: cmdbase-cli
Version: 0.0.1a2
Summary: This module was merged in CMDBase Gitlab repository and is now published on PyPI as cmdbase-utils.
Author-email: Ipamo <dev@ipamo.net>
Project-URL: Homepage, https://gitlab.com/ipamo/cmdbase
Project-URL: Bug Tracker, https://gitlab.com/ipamo/cmdbase/issues
Keywords: cmdb
Classifier: Development Status :: 1 - Planning
Classifier: License :: OSI Approved :: MIT License
Classifier: Operating System :: OS Independent
Classifier: Programming Language :: Python :: 3.11
Requires-Python: >=3.11.2
License-File: LICENSE.txt
